prompt_zen/__init__.py
prompt_zen/enhancer.py
prompt_zen-1.0.1.dist-info/LICENSE
prompt_zen-1.0.1.dist-info/METADATA
prompt_zen-1.0.1.dist-info/WHEEL
prompt_zen-1.0.1.dist-info/top_level.txt
prompt_zen-1.0.1.dist-info/RECORD
