Metadata-Version: 2.1
Name: prompt-zen
Version: 1.0.1
Summary: A framework for iterative prompt refinement and optimization.
Home-page: UNKNOWN
Author: Philipp Heller
License: BSD-3-Clause
Platform: UNKNOWN
Classifier: Programming Language :: Python :: 3
Classifier: License :: OSI Approved :: BSD License
Classifier: Operating System :: OS Independent
Requires-Python: >=3.9
Requires-Dist: pandas>=2.2.3
Requires-Dist: langchain>=0.3.7
